setup.cfg
setup.py
src/techbubbleiotjumpwaymqtt/__init__.py
src/techbubbleiotjumpwaymqtt/application.py
src/techbubbleiotjumpwaymqtt/ca.pem
src/techbubbleiotjumpwaymqtt/device.py
src/techbubbleiotjumpwaymqtt.egg-info/PKG-INFO
src/techbubbleiotjumpwaymqtt.egg-info/SOURCES.txt
src/techbubbleiotjumpwaymqtt.egg-info/dependency_links.txt
src/techbubbleiotjumpwaymqtt.egg-info/requires.txt
src/techbubbleiotjumpwaymqtt.egg-info/top_level.txt