Metadata-Version: 1.0
Name: techbubbleiotjumpwaymqtt
Version: 0.1.3
Summary: TechBubble Technologies IoT JumpWay MQTT Client for Python
Home-page: https://github.com/TechBubbleTechnologies/TechBubble-Iot-JumpWay-Python-MQTT
Author: Adam Milton-Barker
Author-email: adammiltonbarker@gmail.com
License: MIT
Platform: UNKNOWN
